provision_py_proj/__init__.py
provision_py_proj/command_creator.py
provision_py_proj/data_and_config_manager.py
provision_py_proj/license_manager.py
provision_py_proj/main.py
provision_py_proj/pkg_utils.py
provision_py_proj/template_formatter.py
provision_py_proj-0.1.data/scripts/provision_py_proj
provision_py_proj-0.1.dist-info/METADATA
provision_py_proj-0.1.dist-info/RECORD
provision_py_proj-0.1.dist-info/WHEEL
provision_py_proj-0.1.dist-info/top_level.txt
