Metadata-Version: 2.1
Name: provision-py-proj
Version: 0.1
Summary: Utility for the creation of python packages.
Home-page: https://github.com/ku-wolf/provision_py_proj
Author: Kevin Wolf
Author-email: kevinuwolf@gmail.com
License: gplv3.txt
Platform: UNKNOWN
Classifier: Programming Language :: Python :: 3
Classifier: Operating System :: OS Independent
Classifier: License :: OSI Approved :: GNU General Public License v3 (GPLv3)
Requires-Dist: appdirs (>=1.4.3)
Requires-Dist: click (>=7.0)
